{
  "annotations": {
    "list": [
      {
        "builtIn": 1,
        "datasource": {
          "type": "grafana",
          "uid": "-- Grafana --"
        },
        "enable": true,
        "hide": true,
        "iconColor": "rgba(0, 211, 255, 1)",
        "name": "Annotations & Alerts",
        "type": "dashboard"
      }
    ]
  },
  "editable": true,
  "fiscalYearStartMonth": 0,
  "graphTooltip": 0,
  "id": null,
  "links": [],
  "liveNow": false,
  "panels": [
    {
      "datasource": {
        "type": "prometheus",
        "uid": "${datasource}"
      },
      "description": "Session activity over time by page",
      "fieldConfig": {
        "defaults": {
          "color": {
            "mode": "palette-classic"
          },
          "custom": {
            "axisCenteredZero": false,
            "axisColorMode": "text",
            "axisLabel": "Sessions",
            "axisPlacement": "auto",
            "barAlignment": 0,
            "drawStyle": "bars",
            "fillOpacity": 100,
            "gradientMode": "none",
            "hideFrom": {
              "tooltip": false,
              "viz": false,
              "legend": false
            },
            "lineInterpolation": "linear",
            "lineWidth": 1,
            "pointSize": 5,
            "scaleDistribution": {
              "type": "linear"
            },
            "showPoints": "never",
            "spanNulls": false,
            "stacking": {
              "group": "A",
              "mode": "normal"
            },
            "thresholdsStyle": {
              "mode": "off"
            }
          },
          "mappings": [],
          "thresholds": {
            "mode": "absolute",
            "steps": [
              {
                "color": "green",
                "value": null
              }
            ]
          },
          "unit": "short"
        },
        "overrides": []
      },
      "gridPos": {
        "h": 8,
        "w": 24,
        "x": 0,
        "y": 0
      },
      "id": 1,
      "options": {
        "legend": {
          "calcs": [],
          "displayMode": "list",
          "placement": "bottom",
          "showLegend": true
        },
        "tooltip": {
          "mode": "multi",
          "sort": "desc"
        }
      },
      "pluginVersion": "10.2.0",
      "targets": [
        {
          "datasource": {
            "type": "prometheus",
            "uid": "${datasource}"
          },
          "editorMode": "code",
          "expr": "sum by (page_id)(increase(loki_process_custom_faro_session_pageviews_total{app_name=\"$app\"}[$__interval]))",
          "legendFormat": "Page ID: {{page_id}}",
          "range": true,
          "refId": "A"
        }
      ],
      "title": "Sessions Overview",
      "type": "timeseries"
    },
    {
      "datasource": {
        "type": "prometheus",
        "uid": "${datasource}"
      },
      "description": "Total unique sessions",
      "fieldConfig": {
        "defaults": {
          "color": {
            "mode": "thresholds"
          },
          "mappings": [],
          "thresholds": {
            "mode": "absolute",
            "steps": [
              {
                "color": "green",
                "value": null
              }
            ]
          },
          "unit": "short"
        },
        "overrides": []
      },
      "gridPos": {
        "h": 4,
        "w": 4,
        "x": 0,
        "y": 8
      },
      "id": 2,
      "options": {
        "colorMode": "value",
        "graphMode": "area",
        "justifyMode": "center",
        "orientation": "auto",
        "reduceOptions": {
          "calcs": [
            "lastNotNull"
          ],
          "fields": "",
          "values": false
        },
        "textMode": "auto"
      },
      "pluginVersion": "10.2.0",
      "targets": [
        {
          "datasource": {
            "type": "prometheus",
            "uid": "${datasource}"
          },
          "editorMode": "code",
          "expr": "count(sum by (session_id)(increase(loki_process_custom_faro_session_events_total{app_name=\"$app\"}[$__range])) > bool 0)",
          "legendFormat": "Total Sessions",
          "range": true,
          "refId": "A"
        }
      ],
      "title": "Total Sessions",
      "type": "stat"
    },
    {
      "datasource": {
        "type": "prometheus",
        "uid": "${datasource}"
      },
      "description": "Average page views per session",
      "fieldConfig": {
        "defaults": {
          "color": {
            "mode": "thresholds"
          },
          "decimals": 1,
          "mappings": [],
          "thresholds": {
            "mode": "absolute",
            "steps": [
              {
                "color": "green",
                "value": null
              }
            ]
          },
          "unit": "short"
        },
        "overrides": []
      },
      "gridPos": {
        "h": 4,
        "w": 4,
        "x": 4,
        "y": 8
      },
      "id": 3,
      "options": {
        "colorMode": "value",
        "graphMode": "area",
        "justifyMode": "center",
        "orientation": "auto",
        "reduceOptions": {
          "calcs": [
            "lastNotNull"
          ],
          "fields": "",
          "values": false
        },
        "textMode": "auto"
      },
      "pluginVersion": "10.2.0",
      "targets": [
        {
          "datasource": {
            "type": "prometheus",
            "uid": "${datasource}"
          },
          "editorMode": "code",
          "expr": "sum(increase(loki_process_custom_faro_session_pageviews_total{app_name=\"$app\"}[$__range])) / count(sum by (session_id)(increase(loki_process_custom_faro_session_events_total{app_name=\"$app\"}[$__range])) > bool 0)",
          "legendFormat": "Avg Pages/Session",
          "range": true,
          "refId": "A"
        }
      ],
      "title": "Avg Pages/Session",
      "type": "stat"
    },
    {
      "datasource": {
        "type": "prometheus",
        "uid": "${datasource}"
      },
      "description": "Sessions with errors",
      "fieldConfig": {
        "defaults": {
          "color": {
            "mode": "thresholds"
          },
          "mappings": [],
          "thresholds": {
            "mode": "absolute",
            "steps": [
              {
                "color": "green",
                "value": null
              },
              {
                "color": "green",
                "value": 0
              },
              {
                "color": "yellow",
                "value": 1
              },
              {
                "color": "red",
                "value": 10
              }
            ]
          },
          "unit": "short"
        },
        "overrides": []
      },
      "gridPos": {
        "h": 4,
        "w": 4,
        "x": 8,
        "y": 8
      },
      "id": 4,
      "options": {
        "colorMode": "background",
        "graphMode": "area",
        "justifyMode": "center",
        "orientation": "auto",
        "reduceOptions": {
          "calcs": [
            "lastNotNull"
          ],
          "fields": "",
          "values": false
        },
        "textMode": "auto"
      },
      "pluginVersion": "10.2.0",
      "targets": [
        {
          "datasource": {
            "type": "prometheus",
            "uid": "${datasource}"
          },
          "editorMode": "code",
          "expr": "count(sum by (session_id)(increase(loki_process_custom_faro_session_errors_total{app_name=\"$app\"}[$__range])) > bool 0)",
          "legendFormat": "Error Sessions",
          "range": true,
          "refId": "A"
        }
      ],
      "title": "Sessions with Errors",
      "type": "stat"
    },
    {
      "datasource": {
        "type": "prometheus",
        "uid": "${datasource}"
      },
      "description": "Top pages by unique sessions",
      "fieldConfig": {
        "defaults": {
          "color": {
            "mode": "palette-classic"
          },
          "custom": {
            "hideFrom": {
              "tooltip": false,
              "viz": false,
              "legend": false
            }
          },
          "mappings": [],
          "unit": "short"
        },
        "overrides": []
      },
      "gridPos": {
        "h": 8,
        "w": 6,
        "x": 12,
        "y": 8
      },
      "id": 5,
      "options": {
        "displayLabels": ["name", "percent"],
        "legend": {
          "displayMode": "list",
          "placement": "right",
          "showLegend": true
        },
        "pieType": "pie",
        "reduceOptions": {
          "values": false,
          "calcs": [
            "lastNotNull"
          ],
          "fields": ""
        },
        "tooltip": {
          "mode": "single",
          "sort": "none"
        }
      },
      "pluginVersion": "10.2.0",
      "targets": [
        {
          "datasource": {
            "type": "prometheus",
            "uid": "${datasource}"
          },
          "editorMode": "code",
          "expr": "topk(10, count by (page_id)(sum by (session_id, page_id)(increase(loki_process_custom_faro_session_pageviews_total{app_name=\"$app\"}[$__range])) > bool 0))",
          "legendFormat": "{{page_id}}",
          "range": true,
          "refId": "A"
        }
      ],
      "title": "Top Pages by Sessions",
      "type": "piechart"
    },
    {
      "datasource": {
        "type": "prometheus",
        "uid": "${datasource}"
      },
      "description": "Browser distribution across sessions",
      "fieldConfig": {
        "defaults": {
          "color": {
            "mode": "palette-classic"
          },
          "custom": {
            "hideFrom": {
              "tooltip": false,
              "viz": false,
              "legend": false
            }
          },
          "mappings": [],
          "unit": "short"
        },
        "overrides": []
      },
      "gridPos": {
        "h": 8,
        "w": 6,
        "x": 18,
        "y": 8
      },
      "id": 6,
      "options": {
        "displayLabels": ["name", "percent"],
        "legend": {
          "displayMode": "list",
          "placement": "right",
          "showLegend": true
        },
        "pieType": "donut",
        "reduceOptions": {
          "values": false,
          "calcs": [
            "lastNotNull"
          ],
          "fields": ""
        },
        "tooltip": {
          "mode": "single",
          "sort": "none"
        }
      },
      "pluginVersion": "10.2.0",
      "targets": [
        {
          "datasource": {
            "type": "prometheus",
            "uid": "${datasource}"
          },
          "editorMode": "code",
          "expr": "count by (browser_name)(sum by (session_id, browser_name)(increase(loki_process_custom_faro_session_events_total{app_name=\"$app\"}[$__range])) > bool 0)",
          "legendFormat": "{{browser_name}}",
          "range": true,
          "refId": "A"
        }
      ],
      "title": "Browser Distribution",
      "type": "piechart"
    },
    {
      "datasource": {
        "type": "prometheus",
        "uid": "${datasource}"
      },
      "description": "Individual session details with errors and activity",
      "fieldConfig": {
        "defaults": {
          "color": {
            "mode": "thresholds"
          },
          "custom": {
            "align": "auto",
            "cellOptions": {
              "type": "auto"
            },
            "inspect": false
          },
          "mappings": [],
          "thresholds": {
            "mode": "absolute",
            "steps": [
              {
                "color": "green",
                "value": null
              }
            ]
          }
        },
        "overrides": [
          {
            "matcher": {
              "id": "byName",
              "options": "Session ID"
            },
            "properties": [
              {
                "id": "custom.width",
                "value": 150
              },
              {
                "id": "links",
                "value": [
                  {
                    "title": "View Session Details",
                    "url": "/d/session-details?var-session_id=${__value.text}"
                  }
                ]
              }
            ]
          },
          {
            "matcher": {
              "id": "byName",
              "options": "Start Time"
            },
            "properties": [
              {
                "id": "unit",
                "value": "dateTimeAsIso"
              },
              {
                "id": "custom.width",
                "value": 180
              }
            ]
          },
          {
            "matcher": {
              "id": "byName",
              "options": "Errors"
            },
            "properties": [
              {
                "id": "custom.width",
                "value": 80
              },
              {
                "id": "color",
                "value": {
                  "mode": "thresholds"
                }
              },
              {
                "id": "thresholds",
                "value": {
                  "mode": "absolute",
                  "steps": [
                    {
                      "color": "green",
                      "value": null
                    },
                    {
                      "color": "green",
                      "value": 0
                    },
                    {
                      "color": "yellow",
                      "value": 1
                    },
                    {
                      "color": "red",
                      "value": 5
                    }
                  ]
                }
              },
              {
                "id": "custom.cellOptions",
                "value": {
                  "type": "color-background"
                }
              }
            ]
          },
          {
            "matcher": {
              "id": "byName",
              "options": "Page Views"
            },
            "properties": [
              {
                "id": "custom.width",
                "value": 100
              }
            ]
          },
          {
            "matcher": {
              "id": "byName",
              "options": "Browser"
            },
            "properties": [
              {
                "id": "custom.width",
                "value": 150
              }
            ]
          },
          {
            "matcher": {
              "id": "byName",
              "options": "Last Page"
            },
            "properties": [
              {
                "id": "custom.width",
                "value": 200
              }
            ]
          },
          {
            "matcher": {
              "id": "byName",
              "options": "Session Lifecycle"
            },
            "properties": [
              {
                "id": "custom.width",
                "value": 120
              },
              {
                "id": "mappings",
                "value": [
                  {
                    "type": "value",
                    "options": {
                      "0": {
                        "text": "Active",
                        "color": "green"
                      }
                    }
                  },
                  {
                    "type": "range",
                    "options": {
                      "from": 1,
                      "to": 1000000,
                      "result": {
                        "text": "Start",
                        "color": "blue"
                      }
                    }
                  }
                ]
              },
              {
                "id": "custom.cellOptions",
                "value": {
                  "type": "color-text"
                }
              }
            ]
          }
        ]
      },
      "gridPos": {
        "h": 14,
        "w": 24,
        "x": 0,
        "y": 16
      },
      "id": 7,
      "options": {
        "cellHeight": "sm",
        "footer": {
          "countRows": false,
          "enablePagination": true,
          "fields": "",
          "reducer": [
            "sum"
          ],
          "show": false
        },
        "frameIndex": 0,
        "showHeader": true,
        "sortBy": [
          {
            "desc": true,
            "displayName": "Start Time"
          }
        ]
      },
      "pluginVersion": "10.2.0",
      "targets": [
        {
          "datasource": {
            "type": "prometheus",
            "uid": "${datasource}"
          },
          "editorMode": "code",
          "expr": "group by (session_id)(increase(loki_process_custom_faro_session_events_total{app_name=\"$app\"}[1m]))",
          "format": "table",
          "instant": true,
          "refId": "Time"
        },
        {
          "datasource": {
            "type": "prometheus",
            "uid": "${datasource}"
          },
          "editorMode": "code",
          "expr": "sum by (session_id)(increase(loki_process_custom_faro_session_errors_total{app_name=\"$app\"}[$__range]))",
          "format": "table",
          "instant": true,
          "refId": "Errors"
        },
        {
          "datasource": {
            "type": "prometheus",
            "uid": "${datasource}"
          },
          "editorMode": "code",
          "expr": "sum by (session_id)(increase(loki_process_custom_faro_session_pageviews_total{app_name=\"$app\"}[$__range]))",
          "format": "table",
          "instant": true,
          "refId": "PageViews"
        },
        {
          "datasource": {
            "type": "prometheus",
            "uid": "${datasource}"
          },
          "editorMode": "code",
          "expr": "topk by (session_id) (1, max by (session_id, browser_name)(loki_process_custom_faro_session_events_total{app_name=\"$app\"}))",
          "format": "table",
          "instant": true,
          "refId": "Browser"
        },
        {
          "datasource": {
            "type": "prometheus",
            "uid": "${datasource}"
          },
          "editorMode": "code",
          "expr": "topk by (session_id) (1, max by (session_id, page_id)(loki_process_custom_faro_session_pageviews_total{app_name=\"$app\"}))",
          "format": "table",
          "instant": true,
          "refId": "Page"
        },
        {
          "datasource": {
            "type": "prometheus",
            "uid": "${datasource}"
          },
          "editorMode": "code",
          "expr": "sum by (session_id)(increase(loki_process_custom_faro_session_events_total{app_name=\"$app\"}[1m]))",
          "format": "table",
          "instant": true,
          "refId": "Lifecycle"
        }
      ],
      "title": "Sessions",
      "transformations": [
        {
          "id": "merge",
          "options": {}
        },
        {
          "id": "groupBy",
          "options": {
            "fields": {
              "Time": {
                "aggregations": ["max"],
                "operation": "aggregate"
              },
              "Value #Browser": {
                "aggregations": ["lastNotNull"],
                "operation": "aggregate"
              },
              "Value #Errors": {
                "aggregations": ["lastNotNull"],
                "operation": "aggregate"
              },
              "Value #Lifecycle": {
                "aggregations": ["lastNotNull"],
                "operation": "aggregate"
              },
              "Value #Page": {
                "aggregations": ["lastNotNull"],
                "operation": "aggregate"
              },
              "Value #PageViews": {
                "aggregations": ["lastNotNull"],
                "operation": "aggregate"
              },
              "Value #Time": {
                "aggregations": [],
                "operation": "groupby"
              },
              "browser_name": {
                "aggregations": ["lastNotNull"],
                "operation": "aggregate"
              },
              "page_id": {
                "aggregations": ["lastNotNull"],
                "operation": "aggregate"
              },
              "session_id": {
                "aggregations": [],
                "operation": "groupby"
              }
            }
          }
        },
        {
          "id": "organize",
          "options": {
            "excludeByName": {
              "Value #Browser (lastNotNull)": true,
              "Value #Page (lastNotNull)": true,
              "Value #Time": true
            },
            "indexByName": {},
            "renameByName": {
              "Time (max)": "Start Time",
              "Value #Errors (lastNotNull)": "Errors",
              "Value #Lifecycle (lastNotNull)": "Session Lifecycle",
              "Value #PageViews (lastNotNull)": "Page Views",
              "browser_name (lastNotNull)": "Browser",
              "page_id (lastNotNull)": "Last Page",
              "session_id": "Session ID"
            }
          }
        }
      ],
      "type": "table"
    },
    {
      "datasource": {
        "type": "prometheus",
        "uid": "${datasource}"
      },
      "description": "Session navigation flow between pages",
      "fieldConfig": {
        "defaults": {
          "color": {
            "mode": "thresholds"
          },
          "custom": {
            "align": "auto",
            "cellOptions": {
              "type": "auto"
            },
            "inspect": false
          },
          "mappings": [],
          "thresholds": {
            "mode": "absolute",
            "steps": [
              {
                "color": "green",
                "value": null
              }
            ]
          }
        },
        "overrides": [
          {
            "matcher": {
              "id": "byName",
              "options": "From Page"
            },
            "properties": [
              {
                "id": "custom.width",
                "value": 200
              }
            ]
          },
          {
            "matcher": {
              "id": "byName",
              "options": "To Page"
            },
            "properties": [
              {
                "id": "custom.width",
                "value": 200
              }
            ]
          },
          {
            "matcher": {
              "id": "byName",
              "options": "Transitions"
            },
            "properties": [
              {
                "id": "custom.width",
                "value": 100
              },
              {
                "id": "color",
                "value": {
                  "mode": "continuous-GrYlRd"
                }
              },
              {
                "id": "custom.cellOptions",
                "value": {
                  "type": "color-background",
                  "mode": "gradient"
                }
              }
            ]
          }
        ]
      },
      "gridPos": {
        "h": 10,
        "w": 12,
        "x": 0,
        "y": 30
      },
      "id": 8,
      "options": {
        "cellHeight": "sm",
        "footer": {
          "countRows": false,
          "fields": "",
          "reducer": [
            "sum"
          ],
          "show": false
        },
        "showHeader": true,
        "sortBy": [
          {
            "desc": true,
            "displayName": "Transitions"
          }
        ]
      },
      "pluginVersion": "10.2.0",
      "targets": [
        {
          "datasource": {
            "type": "prometheus",
            "uid": "${datasource}"
          },
          "editorMode": "code",
          "expr": "topk(20, sum by (page_path, route_template)(increase(loki_process_custom_faro_session_pageviews_total{app_name=\"$app\"}[$__range])))",
          "format": "table",
          "instant": true,
          "refId": "A"
        }
      ],
      "title": "Page Flow Analysis",
      "transformations": [
        {
          "id": "organize",
          "options": {
            "excludeByName": {
              "Time": true
            },
            "indexByName": {},
            "renameByName": {
              "Value": "Transitions",
              "page_path": "From Page",
              "route_template": "To Page"
            }
          }
        }
      ],
      "type": "table"
    },
    {
      "datasource": {
        "type": "prometheus",
        "uid": "${datasource}"
      },
      "description": "Session error rates over time",
      "fieldConfig": {
        "defaults": {
          "color": {
            "mode": "palette-classic"
          },
          "custom": {
            "axisCenteredZero": false,
            "axisColorMode": "text",
            "axisLabel": "",
            "axisPlacement": "auto",
            "barAlignment": 0,
            "drawStyle": "line",
            "fillOpacity": 10,
            "gradientMode": "none",
            "hideFrom": {
              "tooltip": false,
              "viz": false,
              "legend": false
            },
            "lineInterpolation": "linear",
            "lineWidth": 2,
            "pointSize": 5,
            "scaleDistribution": {
              "type": "linear"
            },
            "showPoints": "never",
            "spanNulls": false,
            "stacking": {
              "group": "A",
              "mode": "none"
            },
            "thresholdsStyle": {
              "mode": "off"
            }
          },
          "mappings": [],
          "thresholds": {
            "mode": "absolute",
            "steps": [
              {
                "color": "green",
                "value": null
              }
            ]
          },
          "unit": "percent"
        },
        "overrides": []
      },
      "gridPos": {
        "h": 10,
        "w": 12,
        "x": 12,
        "y": 30
      },
      "id": 9,
      "options": {
        "legend": {
          "calcs": ["mean", "lastNotNull"],
          "displayMode": "list",
          "placement": "bottom",
          "showLegend": true
        },
        "tooltip": {
          "mode": "multi",
          "sort": "desc"
        }
      },
      "pluginVersion": "10.2.0",
      "targets": [
        {
          "datasource": {
            "type": "prometheus",
            "uid": "${datasource}"
          },
          "editorMode": "code",
          "expr": "100 * (sum(rate(loki_process_custom_faro_session_errors_total{app_name=\"$app\"}[5m])) / sum(rate(loki_process_custom_faro_session_events_total{app_name=\"$app\"}[5m])))",
          "legendFormat": "Error Rate",
          "range": true,
          "refId": "A"
        },
        {
          "datasource": {
            "type": "prometheus",
            "uid": "${datasource}"
          },
          "editorMode": "code",
          "expr": "100 * (count(sum by (session_id)(increase(loki_process_custom_faro_session_errors_total{app_name=\"$app\"}[5m])) > bool 0) / count(sum by (session_id)(increase(loki_process_custom_faro_session_events_total{app_name=\"$app\"}[5m])) > bool 0))",
          "legendFormat": "Sessions with Errors %",
          "range": true,
          "refId": "B"
        }
      ],
      "title": "Session Error Rates",
      "type": "timeseries"
    }
  ],
  "refresh": "30s",
  "schemaVersion": 38,
  "style": "dark",
  "tags": ["sessions", "user-behavior", "faro", "analytics"],
  "templating": {
    "list": [
      {
        "current": {
          "selected": false,
          "text": "Prometheus",
          "value": "prometheus"
        },
        "hide": 0,
        "includeAll": false,
        "label": "Data Source",
        "multi": false,
        "name": "datasource",
        "options": [],
        "query": "prometheus",
        "queryValue": "",
        "refresh": 1,
        "regex": "",
        "skipUrlSync": false,
        "type": "datasource"
      },
      {
        "current": {
          "selected": false,
          "text": "",
          "value": ""
        },
        "datasource": {
          "type": "prometheus",
          "uid": "${datasource}"
        },
        "definition": "label_values(loki_process_custom_faro_session_events_total, app_name)",
        "hide": 0,
        "includeAll": false,
        "label": "Application",
        "multi": false,
        "name": "app",
        "options": [],
        "query": {
          "query": "label_values(loki_process_custom_faro_session_events_total, app_name)",
          "refId": "PrometheusVariableQueryEditor-VariableQuery"
        },
        "refresh": 1,
        "regex": "",
        "skipUrlSync": false,
        "sort": 1,
        "type": "query"
      },
      {
        "current": {
          "selected": false,
          "text": "",
          "value": ""
        },
        "datasource": {
          "type": "prometheus",
          "uid": "${datasource}"
        },
        "definition": "label_values(loki_process_custom_faro_session_events_total{app_name=\"$app\"}, session_id)",
        "hide": 0,
        "includeAll": true,
        "label": "Session ID",
        "multi": false,
        "name": "session_id",
        "options": [],
        "query": {
          "query": "label_values(loki_process_custom_faro_session_events_total{app_name=\"$app\"}, session_id)",
          "refId": "PrometheusVariableQueryEditor-VariableQuery"
        },
        "refresh": 2,
        "regex": "",
        "skipUrlSync": false,
        "sort": 0,
        "type": "query"
      }
    ]
  },
  "time": {
    "from": "now-1h",
    "to": "now"
  },
  "timepicker": {},
  "timezone": "",
  "title": "Session Explorer",
  "uid": "faro-session-explorer",
  "version": 1,
  "weekStart": ""
}

